treelab/__init__.py
treelab/math_tools.py
treelab/misc.py
treelab/cgns/__init__.py
treelab/cgns/base.py
treelab/cgns/node.py
treelab/cgns/tree.py
treelab/cgns/utils.py
treelab/cgns/zone.py
treelab/cgns/mesh/__init__.py
treelab/cgns/mesh/curves/__init__.py
treelab/cgns/mesh/curves/line.py
treelab/cgns/mesh/curves/point.py
treelab/cgns/read_write/__init__.py
treelab/cgns/read_write/h5py2cgns.py
treelab/cgns/test/test_node.py
treelab/cgns/test/test_utils.py
treelab/cgns/test/test_zone.py
treelab/gui/__init__.py
treelab/gui/main.py
treelab/gui/icons/OwnIcons/add-curve-16.png
treelab/gui/icons/OwnIcons/field-16.png
treelab/gui/icons/OwnIcons/folder-horizontal-open-plus.png
treelab/gui/icons/OwnIcons/plus-small.png
treelab/gui/icons/OwnIcons/remove-curve-16.png
treelab/gui/icons/OwnIcons/see-curve-16.png
treelab/gui/icons/OwnIcons/x-16.png
treelab/gui/icons/OwnIcons/y-16.png
treelab/gui/icons/fugue-icons-3.5.6/arrow-circle-double.png
treelab/gui/icons/fugue-icons-3.5.6/arrow-circle.png
treelab/gui/icons/fugue-icons-3.5.6/arrow-switch.png
treelab/gui/icons/fugue-icons-3.5.6/blue-document-copy.png
treelab/gui/icons/fugue-icons-3.5.6/border-left.png
treelab/gui/icons/fugue-icons-3.5.6/clipboard-paste.png
treelab/gui/icons/fugue-icons-3.5.6/compile.png
treelab/gui/icons/fugue-icons-3.5.6/cross.png
treelab/gui/icons/fugue-icons-3.5.6/disk--arrow.png
treelab/gui/icons/fugue-icons-3.5.6/disk--plus.png
treelab/gui/icons/fugue-icons-3.5.6/disk.png
treelab/gui/icons/fugue-icons-3.5.6/external.png
treelab/gui/icons/fugue-icons-3.5.6/folder-horizontal-open.png
treelab/gui/icons/fugue-icons-3.5.6/magnifier--arrow.png
treelab/gui/icons/fugue-icons-3.5.6/magnifier-zoom-in.png
treelab/gui/icons/fugue-icons-3.5.6/magnifier-zoom-out.png
treelab/gui/icons/fugue-icons-3.5.6/node-magnifier.png
treelab/gui/icons/fugue-icons-3.5.6/plug-disconnect.png
treelab/gui/icons/fugue-icons-3.5.6/plus.png
treelab/gui/icons/fugue-icons-3.5.6/scissors-blue.png
mola_treelab-0.4.5.dist-info/METADATA
mola_treelab-0.4.5.dist-info/WHEEL
mola_treelab-0.4.5.dist-info/entry_points.txt
mola_treelab-0.4.5.dist-info/licenses/LICENSE
mola_treelab-0.4.5.dist-info/RECORD
