Metadata-Version: 2.4
Name: mola-treelab
Version: 0.4.5
Summary: MOLA-treelab is an ONERA code that implements an interface to CGNS
Project-URL: Homepage, https://github.com/Luispain/treelab
Project-URL: Issues, https://github.com/Luispain/treelab/issues
Author-email: Luis Bernardos <luisfco.bernardos@gmail.com>, Thomas Bontemps <thomas.bontemps@hotmail.fr>
License: LGPL-3.0-only
License-File: LICENSE
Classifier: License :: OSI Approved :: GNU Lesser General Public License v3 (LGPLv3)
Classifier: Operating System :: OS Independent
Classifier: Programming Language :: Python :: 3
Requires-Python: >=3.7
Requires-Dist: h5py>=3.7.0
Requires-Dist: matplotlib>3.6.2; python_version >= '3.8'
Requires-Dist: numpy>=1.21.0
Requires-Dist: pyqt5; python_version < '3.8'
Requires-Dist: pyside6
Requires-Dist: qtvscodestyle
Provides-Extra: test
Requires-Dist: pytest; extra == 'test'
